LICENSE
README.rst
setup.py
prontonet/__init__.py
prontonet/constants.py
prontonet/device.py
prontonet/enums.py
prontonet/protocol.py
prontonet/structures.py
prontonet_py.egg-info/PKG-INFO
prontonet_py.egg-info/SOURCES.txt
prontonet_py.egg-info/dependency_links.txt
prontonet_py.egg-info/not-zip-safe
prontonet_py.egg-info/top_level.txt