Metadata-Version: 2.1
Name: prontonet-py
Version: 0.0.1
Summary: Python SDK library for Prontonet Family v2.5.4
Home-page: UNKNOWN
Author: avc
Author-email: avcsec@protonmail.com
License: MIT
Platform: UNKNOWN
License-File: LICENSE
